{"version":"0.0.0","name":"amplify-app","dependencies":{"@angular/animations":{"version":"12.2.6"},"@angular/common":{"version":"12.2.6"},"@angular/compiler":{"version":"12.2.6"},"@angular/core":{"version":"12.2.6"},"@angular/forms":{"version":"12.2.6"},"@angular/platform-browser-dynamic":{"version":"12.2.6"},"@angular/platform-browser":{"version":"12.2.6"},"@angular/router":{"version":"12.2.6"},"@aws-amplify/ui-angular":{"version":"1.0.24"},"aws-amplify":{"version":"4.2.9"},"bootstrap-icons":{"version":"1.5.0"},"bootstrap":{"version":"4.6.0"},"buffer":{"version":"6.0.3"},"ngx-bootstrap":{"version":"7.1.0"},"rxjs":{"version":"6.6.7"},"tslib":{"version":"2.3.1"},"zone.js":{"version":"0.11.4"}}}